pybooklid/__init__.py
pybooklid/macbook_lid.py
pybooklid/examples/creak_synthesizer.py
pybooklid/examples/creaky_door.py
pybooklid/examples/monitor_app.py
pybooklid/examples/realistic_creak.py
pybooklid/examples/simple_usage.py
pybooklid-1.0.0.dist-info/licenses/LICENSE.md
pybooklid-1.0.0.dist-info/METADATA
pybooklid-1.0.0.dist-info/WHEEL
pybooklid-1.0.0.dist-info/entry_points.txt
pybooklid-1.0.0.dist-info/top_level.txt
pybooklid-1.0.0.dist-info/RECORD
