Metadata-Version: 2.4
Name: pybooklid
Version: 1.0.0
Summary: MacBook lid angle sensor library for Python
Home-page: https://github.com/tcsenpai/pybooklid
Author: tcsenpai
Author-email: tcsenpai <tcsenpai@discus.sh>
License: MIT
Project-URL: Homepage, https://github.com/tcsenpai/pybooklid
Project-URL: Bug Reports, https://github.com/tcsenpai/pybooklid/issues
Project-URL: Source Code, https://github.com/tcsenpai/pybooklid
Keywords: macbook,lid,angle,sensor,hid,macos,hardware
Classifier: Development Status :: 4 - Beta
Classifier: Intended Audience :: Developers
Classifier: Topic :: System :: Hardware :: Hardware Drivers
Classifier: License :: OSI Approved :: MIT License
Classifier: Programming Language :: Python :: 3
Classifier: Programming Language :: Python :: 3.7
Classifier: Programming Language :: Python :: 3.8
Classifier: Programming Language :: Python :: 3.9
Classifier: Programming Language :: Python :: 3.10
Classifier: Programming Language :: Python :: 3.11
Classifier: Programming Language :: Python :: 3.12
Classifier: Operating System :: MacOS
Classifier: Environment :: MacOS X
Requires-Python: >=3.7
License-File: LICENSE.md
Requires-Dist: hidapi>=0.14.0
Provides-Extra: audio
Requires-Dist: numpy>=1.20.0; extra == "audio"
Requires-Dist: sounddevice>=0.4.0; extra == "audio"
Requires-Dist: scipy>=1.7.0; extra == "audio"
Provides-Extra: dev
Requires-Dist: pytest>=6.0; extra == "dev"
Requires-Dist: black; extra == "dev"
Requires-Dist: flake8; extra == "dev"
Requires-Dist: mypy; extra == "dev"
Dynamic: author
Dynamic: home-page
Dynamic: license-file
Dynamic: requires-python
